README.md
setup.py
bin/stowtui
stowtui/__init__.py
stowtui/stowApp.py
stowtui.egg-info/PKG-INFO
stowtui.egg-info/SOURCES.txt
stowtui.egg-info/dependency_links.txt
stowtui.egg-info/requires.txt
stowtui.egg-info/top_level.txt
stowtui/helpers/__init__.py
stowtui/helpers/meta.py
stowtui/stowtui_core/__init__.py
stowtui/stowtui_core/stowtui_core.py
stowtui/template_interface/DotfilesDirectories.py
stowtui/template_interface/FileManagerTui.py
stowtui/template_interface/__init__.py
stowtui/template_interface/help_ui.py