Metadata-Version: 2.1
Name: stowtui
Version: 1.1.3
Summary: stow tui is a Terminal User Interface Program for GNU STOW
Home-page: https://github.com/ypraw/stowtui
Author: Yunindyo Prabowo
Author-email: Yunindyo.prabowo@gmail.com
License: gpl-3.0
Keywords: stowtui stow dotfiles tui
Platform: UNKNOWN
Classifier: Development Status :: 5 - Production/Stable
Classifier: Intended Audience :: Information Technology
Classifier: License :: OSI Approved :: GNU General Public License v3 or later (GPLv3+)
Classifier: Programming Language :: Python :: 3.6
Classifier: Programming Language :: Python :: 3.7
Classifier: Programming Language :: Python :: 3.8
Requires-Python: >=3.6
